{
    "name": "Ownership",
    "checks": [
        {
            "check_type": "inheritance",
            "parent_names": ["_regex:ownable.*", "ownership", "owner"]
        },
        {
            "check_type": "modifier",
            "modifiers": ["onlyowner", "only_owner", "owner", "owned"]
        },
        {
            "check_type": "comparison",
            "binary_operations": [
                {
                    "operator": "==",
                    "operand_1": "msg.sender",
                    "operand_2": "owner"
                },
                {
                    "operator": "==",
                    "operand_1": "msgsender",
                    "operand_2": "owner"
                }
            ]
        }
    ]
}